axforchemistry/__init__.py
axforchemistry/axforchemistry_.py
axforchemistry/tests/test_sobol.py
axforchemistry/utils/__init__.py
axforchemistry/utils/data.py
axforchemistry/utils/experiment.py
axforchemistry/utils/fractional.py
axforchemistry/utils/metrics.py
axforchemistry/utils/plotting.py
axforchemistry/utils/save.py
axforchemistry/utils/search.py
axforchemistry/utils/sobol.py
axforchemistry-0.1.5.dist-info/LICENSE
axforchemistry-0.1.5.dist-info/WHEEL
axforchemistry-0.1.5.dist-info/METADATA
axforchemistry-0.1.5.dist-info/RECORD
