Metadata-Version: 2.1
Name: axforchemistry
Version: 0.1.5
Summary: Bayesian optimization of formulations via Adaptive Experimentation (Ax) platform.
Author-email: "Sterling G. Baird" <sterling.baird@utah.edu>, Ramsey Issa <u1374011@utah.edu>
Requires-Python: >=3.7
Classifier: License :: OSI Approved :: MIT License
Requires-Dist: numpy
Requires-Dist: pandas
Requires-Dist: plotly
Requires-Dist: ax_platform>=0.2.4
Requires-Dist: pyro-ppl==1.8.1
Requires-Dist: kaleido
Requires-Dist: tqdm
Requires-Dist: matplotlib
Requires-Dist: scipy
Requires-Dist: ipython
Requires-Dist: scikit_learn
Project-URL: Home, https://github.com/sparks-baird/AxForChemistry
